LICENSE
MANIFEST.in
README.md
setup.py
src/cms/__init__.py
src/cms/admin.py
src/cms/context_processors.py
src/cms/debug.py
src/cms/externals.py
src/cms/forms.py
src/cms/html.py
src/cms/loader.py
src/cms/middleware.py
src/cms/permalinks.py
src/cms/sitemaps.py
src/cms/tests.py
src/cms/views.py
src/cms/apps/__init__.py
src/cms/apps/links/__init__.py
src/cms/apps/links/models.py
src/cms/apps/links/tests.py
src/cms/apps/links/urls.py
src/cms/apps/links/views.py
src/cms/apps/links/migrations/0001_initial.py
src/cms/apps/links/migrations/__init__.py
src/cms/apps/links/static/links/img/link.png
src/cms/apps/media/__init__.py
src/cms/apps/media/admin.py
src/cms/apps/media/models.py
src/cms/apps/media/migrations/0001_initial.py
src/cms/apps/media/migrations/__init__.py
src/cms/apps/media/static/media/img/audio-x-generic.png
src/cms/apps/media/static/media/img/image-x-generic.png
src/cms/apps/media/static/media/img/text-x-generic-template.png
src/cms/apps/media/static/media/img/text-x-generic.png
src/cms/apps/media/static/media/img/video-x-generic.png
src/cms/apps/media/static/media/img/x-office-document.png
src/cms/apps/media/static/media/img/x-office-spreadsheet.png
src/cms/apps/media/static/media/js/jquery.cms.media.js
src/cms/apps/media/templates/admin/media/file/change_form.html
src/cms/apps/media/templates/admin/media/file/change_list.html
src/cms/apps/media/templates/admin/media/file/filebrowser_add_success.html
src/cms/apps/media/templates/admin/media/file/tinymce_popup_injection.html
src/cms/apps/news/__init__.py
src/cms/apps/news/admin.py
src/cms/apps/news/models.py
src/cms/apps/news/urls.py
src/cms/apps/news/views.py
src/cms/apps/news/migrations/0001_initial.py
src/cms/apps/news/migrations/__init__.py
src/cms/apps/news/static/news/img/news-feed.png
src/cms/apps/news/templates/news/article_archive.html
src/cms/apps/news/templates/news/article_archive_day.html
src/cms/apps/news/templates/news/article_archive_month.html
src/etianen_cms.egg-info/PKG-INFO
src/etianen_cms.egg-info/SOURCES.txt
src/etianen_cms.egg-info/dependency_links.txt
src/etianen_cms.egg-info/entry_points.txt
src/etianen_cms.egg-info/not-zip-safe
src/etianen_cms.egg-info/requires.txt
src/etianen_cms.egg-info/top_level.txt
