Metadata-Version: 1.1
Name: etianen-cms
Version: 2.6.5
Summary: A collection of Django extensions that add content-management facilities to Django projects.
Home-page: http://github.com/etianen/cms
Author: Dave Hall
Author-email: dave@etianen.com
License: UNKNOWN
Platform: UNKNOWN
Classifier: Development Status :: 5 - Production/Stable
Classifier: Environment :: Web Environment
Classifier: Intended Audience :: Developers
Classifier: License :: OSI Approved :: BSD License
Classifier: Operating System :: OS Independent
Classifier: Programming Language :: Python
Classifier: Framework :: Django
